devisay/__init__.py
devisay/devisay.py
devisay-0.1.2.dist-info/METADATA
devisay-0.1.2.dist-info/WHEEL
devisay-0.1.2.dist-info/top_level.txt
devisay-0.1.2.dist-info/RECORD
