Metadata-Version: 2.4
Name: devisay
Version: 0.1.2
Summary: A small package for funny ASCII prints
Author: Alwyn Quadras
Author-email: alwynquad2002@gmail.com
Classifier: Programming Language :: Python :: 3
Requires-Python: >=3.6
Dynamic: author
Dynamic: author-email
Dynamic: classifier
Dynamic: description
Dynamic: description-content-type
Dynamic: requires-python
Dynamic: summary
